SunTools/Sun.py
SunTools/__init__.py
SunTools-1.5.0.dist-info/LICENSE
SunTools-1.5.0.dist-info/METADATA
SunTools-1.5.0.dist-info/WHEEL
SunTools-1.5.0.dist-info/top_level.txt
SunTools-1.5.0.dist-info/RECORD
