Metadata-Version: 2.1
Name: SunTools
Version: 1.5.0
Summary: Sunrise, sunset, sun altitude and solar flux routines
Home-page: https://github.com/heharkon/SunTools
Author: Henrik Härkönen
Author-email: heharkon@iki.fi
License: UNKNOWN
Project-URL: Bug Tracker, https://github.com/heharkon/SunTools/issues
Platform: UNKNOWN
Classifier: Programming Language :: Python :: 3
Classifier: License :: Public Domain
Classifier: Operating System :: OS Independent
Requires-Python: >=3.5
License-File: LICENSE
